setup.py
django_orm/__init__.py
django_orm/dispatch.py
django_orm/expressions.py
django_orm/manager.py
django_orm/pool.py
django_orm/query_utils.py
django_orm/utils.py
django_orm.egg-info/PKG-INFO
django_orm.egg-info/SOURCES.txt
django_orm.egg-info/dependency_links.txt
django_orm.egg-info/not-zip-safe
django_orm.egg-info/requires.txt
django_orm.egg-info/top_level.txt
django_orm/backends/__init__.py
django_orm/backends/mysql/__init__.py
django_orm/backends/mysql/base.py
django_orm/backends/mysql/creation.py
django_orm/backends/mysql/pool.py
django_orm/backends/postgresql_psycopg2/__init__.py
django_orm/backends/postgresql_psycopg2/base.py
django_orm/backends/postgresql_psycopg2/creation.py
django_orm/backends/postgresql_psycopg2/operations.py
django_orm/backends/postgresql_psycopg2/pool.py
django_orm/backends/postgresql_psycopg2/version.py
django_orm/backends/sqlite3/__init__.py
django_orm/backends/sqlite3/base.py
django_orm/backends/sqlite3/creation.py
django_orm/backends/sqlite3/pool.py
django_orm/cache/__init__.py
django_orm/cache/exceptions.py
django_orm/cache/invalidator.py
django_orm/cache/models.py
django_orm/cache/query.py
django_orm/cache/utils.py
django_orm/fields/__init__.py
django_orm/fields/standard.py
django_orm/gis/__init__.py
django_orm/gis/manager.py
django_orm/gis/query.py
django_orm/gis/db/__init__.py
django_orm/gis/db/backends/__init__.py
django_orm/gis/db/backends/postgis/__init__.py
django_orm/gis/db/backends/postgis/base.py
django_orm/mysql/__init__.py
django_orm/mysql/constants.py
django_orm/mysql/query.py
django_orm/postgresql/__init__.py
django_orm/postgresql/aggregates.py
django_orm/postgresql/constants.py
django_orm/postgresql/query.py
django_orm/postgresql/fields/__init__.py
django_orm/postgresql/fields/arrays.py
django_orm/postgresql/fields/bytea.py
django_orm/postgresql/fields/interval.py
django_orm/postgresql/fts/__init__.py
django_orm/postgresql/fts/fields.py
django_orm/postgresql/fts/mixin.py
django_orm/postgresql/geometric/__init__.py
django_orm/postgresql/geometric/fields.py
django_orm/postgresql/geometric/objects.py
django_orm/postgresql/hstore/__init__.py
django_orm/postgresql/hstore/fields.py
